Workbook

Sheet Summary
A1: Farmers Cooperative Tub Line - Cost to Price
A2: INTERNAL. All costs are MCE budget estimates for review; replace with vendor quotes as they come in.
A4: Area | B4: Cost ($) | C4: Share of cost | D4: Sell at target margin ($) | E4: Proposal price ($) | F4: Margin at proposal
A5: A. Dry ingredients | B5: =SUMIFS('Cost Build'!$K$2:$K$35,'Cost Build'!$A$2:$A$35,A5) | C5: =IFERROR(B5/$B$14,0) | D5: =B5*(1+Inputs!$B$12)/(1-Inputs!$B$11) | E5: 275550 | F5: =IFERROR(1-B5*(1+Inputs!$B$12)/E5,0)
A6: B. Molasses | B6: =SUMIFS('Cost Build'!$K$2:$K$35,'Cost Build'!$A$2:$A$35,A6) | C6: =IFERROR(B6/$B$14,0) | D6: =B6*(1+Inputs!$B$12)/(1-Inputs!$B$11) | E6: 149200 | F6: =IFERROR(1-B6*(1+Inputs!$B$12)/E6,0)
A7: C. 3-stage cook | B7: =SUMIFS('Cost Build'!$K$2:$K$35,'Cost Build'!$A$2:$A$35,A7) | C7: =IFERROR(B7/$B$14,0) | D7: =B7*(1+Inputs!$B$12)/(1-Inputs!$B$11) | E7: 458045 | F7: =IFERROR(1-B7*(1+Inputs!$B$12)/E7,0)
A8: D. Pour turntable | B8: =SUMIFS('Cost Build'!$K$2:$K$35,'Cost Build'!$A$2:$A$35,A8) | C8: =IFERROR(B8/$B$14,0) | D8: =B8*(1+Inputs!$B$12)/(1-Inputs!$B$11) | E8: 121400 | F8: =IFERROR(1-B8*(1+Inputs!$B$12)/E8,0)
A9: E. Cure tunnel | B9: =SUMIFS('Cost Build'!$K$2:$K$35,'Cost Build'!$A$2:$A$35,A9) | C9: =IFERROR(B9/$B$14,0) | D9: =B9*(1+Inputs!$B$12)/(1-Inputs!$B$11) | E9: 168125 | F9: =IFERROR(1-B9*(1+Inputs!$B$12)/E9,0)
A10: F. Robot and wrap | B10: =SUMIFS('Cost Build'!$K$2:$K$35,'Cost Build'!$A$2:$A$35,A10) | C10: =IFERROR(B10/$B$14,0) | D10: =B10*(1+Inputs!$B$12)/(1-Inputs!$B$11) | E10: 207815 | F10: =IFERROR(1-B10*(1+Inputs!$B$12)/E10,0)
A11: G. Controls | B11: =SUMIFS('Cost Build'!$K$2:$K$35,'Cost Build'!$A$2:$A$35,A11) | C11: =IFERROR(B11/$B$14,0) | D11: =B11*(1+Inputs!$B$12)/(1-Inputs!$B$11) | E11: 260745 | F11: =IFERROR(1-B11*(1+Inputs!$B$12)/E11,0)
A12: H. Engineering | B12: =SUMIFS('Cost Build'!$K$2:$K$35,'Cost Build'!$A$2:$A$35,A12) | C12: =IFERROR(B12/$B$14,0) | D12: =B12*(1+Inputs!$B$12)/(1-Inputs!$B$11) | E12: 104170 | F12: =IFERROR(1-B12*(1+Inputs!$B$12)/E12,0)
A13: I. Start-up services | B13: =SUMIFS('Cost Build'!$K$2:$K$35,'Cost Build'!$A$2:$A$35,A13) | C13: =IFERROR(B13/$B$14,0) | D13: =B13*(1+Inputs!$B$12)/(1-Inputs!$B$11) | E13: 13800 | F13: =IFERROR(1-B13*(1+Inputs!$B$12)/E13,0)
A14: Base cost | B14: =SUM(B5:B13) | C14: =SUM(C5:C13) | D14: =SUM(D5:D13) | E14: =SUM(E5:E13) | F14: =IFERROR(1-B16/E14,0)
A15: Contingency | B15: =B14*Inputs!$B$12 | E15: Proposal area prices per MCE-Q-2610-FCO-R1
A16: Total cost with contingency | B16: =B14+B15
A17: Proposal sell price (R1) | B17: =Inputs!$B$13 | C17: ="Target-margin price: "&TEXT(B16/(1-Inputs!$B$11),"$#,##0")
A18: Gross profit | B18: =B17-B16
A19: Gross margin at proposal price | B19: =IFERROR(B18/B17,0)
A20: Margin sensitivity
A21: Gross margin | B21: Sell, with robot ($) | C21: Sell, manual stacking ($)
A22: 0.4 | B22: =$B$16/(1-A22) | C22: =($B$16-$B$27*(1+Inputs!$B$12)+$B$28*(1+Inputs!$B$12))/(1-A22)
A23: 0.45 | B23: =$B$16/(1-A23) | C23: =($B$16-$B$27*(1+Inputs!$B$12)+$B$28*(1+Inputs!$B$12))/(1-A23)
A24: 0.5 | B24: =$B$16/(1-A24) | C24: =($B$16-$B$27*(1+Inputs!$B$12)+$B$28*(1+Inputs!$B$12))/(1-A24)
A25: 0.55 | B25: =$B$16/(1-A25) | C25: =($B$16-$B$27*(1+Inputs!$B$12)+$B$28*(1+Inputs!$B$12))/(1-A25)
A27: Robot cell cost (tagged 'Robot') | B27: =SUMIFS('Cost Build'!$K$2:$K$35,'Cost Build'!$M$2:$M$35,"Robot")
A28: Manual lift-assist station cost instead | B28: 25000 | C28: Assumed lift-assist stacking station cost
A30: Benchmark check
A31: Press tub plant, 2022 sell (3 lines) | B31: =Inputs!$B$16
A32: Escalated to 2026 dollars | B32: =B31*(1+Inputs!$B$17)
A33: This line's sell as share of benchmark | B33: =IFERROR(B17/B32,0)
A35: Schedule (speed to start-up)
A36: Engineering before orders release (wks) | B36: =Inputs!$B$20
A37: Longest equipment lead time (wks) | B37: =MAX('Cost Build'!$L$2:$L$35)
A38: Longest-lead item | B38: =INDEX('Cost Build'!$B$2:$B$35,MATCH(B37,'Cost Build'!$L$2:$L$35,0))
A39: Installation + commissioning (wks) | B39: =Inputs!$B$21+Inputs!$B$22
A40: Order to start-up (wks) | B40: =B36+B37+B39

Sheet Customer ROI
A1: Farmers Cooperative - Make vs Buy ROI
A2: Blue = assumption. Replace buy price and ingredient cost with Farmers Cooperative's actual numbers.
A4: Input | B4: Base case | C4: Conservative | D4: Notes
A5: Line price ($) | B5: 1758850 | C5: 1758850 | D5: Proposal MCE-Q-2610-FCO-R1 sell price
A6: Annual volume (tons) | B6: 5000 | C6: 5000 | D6: Per Jason: ~5,000 tons/yr total
A7: Tub size (lb) | B7: 225 | C7: 225 | D7: 225 lb equivalent tubs
A8: Current buy price per tub ($) | B8: 115 | C8: 100.05 | D8: ASSUMED, mix-weighted (30-13 $115, 38 HI-E $125, 17 +Mag $105); conservative 13% lower
A9: Blended ingredient cost ($/ton) | B9: 458.9 | C9: 504.79 | D9: Finished cost from estimated formulas, mix-weighted 50/25/25; conservative +10%
A10: Tub, lid and label ($/tub) | B10: 14 | C10: 15 | D10: ASSUMED plastic 225 lb tub
A11: Operators on line | B11: 4 | C11: 4 | D11: One shift
A12: Loaded labor rate ($/hr) | B12: 28 | C12: 28 | D12: ASSUMED
A13: Hours per year per operator | B13: 2080 | C13: 2080 | D13: One shift, full year
A14: Energy ($/tub) | B14: 1 | C14: 1.25 | D14: ASSUMED gas + electric
A15: Maintenance (% of line price per yr) | B15: 0.03 | C15: 0.03 | D15: ASSUMED
A17: Results
A18: Tubs per year | B18: =B6*2000/B7 | C18: =C6*2000/C7
A19: Ingredients per tub ($) | B19: =B9*B7/2000 | C19: =C9*C7/2000
A20: Labor per tub ($) | B20: =IFERROR(B11*B12*B13/B18,0) | C20: =IFERROR(C11*C12*C13/C18,0)
A21: Maintenance per tub ($) | B21: =IFERROR(B5*B15/B18,0) | C21: =IFERROR(C5*C15/C18,0)
A22: Cost to make per tub ($) | B22: =B19+B10+B20+B14+B21 | C22: =C19+C10+C20+C14+C21
A23: Savings per tub vs buying ($) | B23: =B8-B22 | C23: =C8-C22
A24: Annual savings ($) | B24: =B23*B18 | C24: =C23*C18
A25: Simple payback (years) | B25: =IFERROR(B5/B24,0) | C25: =IFERROR(C5/C24,0)
A26: Simple payback (months) | B26: =IFERROR(12*B5/B24,0) | C26: =IFERROR(12*C5/C24,0)
A27: 5-year net savings ($) | B27: =5*B24-B5 | C27: =5*C24-C5
A28: Break-even tubs per year | B28: =IFERROR(B5/B23,0) | C28: =IFERROR(C5/C23,0)
A30: Sources: retail price check - https://nrsworld.com/products/30-13-cooked-plastic-protein-tub ; https://tractorsupply.com/tsc/product/purina-rangeland-30-13-beef-cattle-protein-tub-225-pound-(225-lb)-tub-225-lb

Sheet Inputs
A1: Farmers Cooperative Tub Line - Cost Model Inputs
A2: INTERNAL - MCE cost basis. Blue = editable input. Yellow = key assumption to confirm.
A4: Labor rates ($/hr, burdened cost)
A5: Shop | B5: 65 | C5: Assumed MCE shop fabrication cost rate - confirm
A6: Eng | B6: 95 | C6: Assumed engineering/design cost rate - confirm
A7: Controls | B7: 110 | C7: Assumed controls programming/integration cost rate - confirm
A8: Field | B8: 70 | C8: Assumed field install crew cost rate - confirm
A10: Pricing
A11: Target gross margin | B11: 0.5 | C11: Per Jason: custom systems priced at 50% margin (sell = 2x cost)
A12: Contingency on cost | B12: 0.05 | C12: Covers scope growth before FEED fixes the design
A13: Proposal sell price | B13: 1758850 | C13: Proposal MCE-Q-2610-FCO-R1, Oct 20 2026: equipment, engineering, start-up; installation and freight by others
A15: Benchmark: previous press tub plant
A16: 2022 sell price (3 press lines) | B16: 1300000 | C16: Per Jason: approx. $1.3M in 2022; 3 press lines
A17: Escalation 2022 to 2026 | B17: 0.18 | C17: Assumed steel/labor/equipment inflation 2022-2026 - confirm
A19: Schedule (weeks)
A20: FEED + detailed engineering | B20: 8 | C20: Assumed; runs before long-lead orders release
A21: Installation (by others) | B21: 6 | C21: Customer contractor; drives start-up date
A22: Commissioning and training | B22: 2 | C22: Assumed

Sheet Cost Build
A1: Area | B1: Item | C1: Type | D1: Qty | E1: Unit material / buyout ($) | F1: Labor hrs / unit | G1: Labor class | H1: Material ($) | I1: Labor hrs | J1: Labor ($) | K1: Total cost ($) | L1: Lead time (wks) | M1: Option tag | N1: Notes
A2: A. Dry ingredients | B2: Tote unloader frame, hopper and metering screw | C2: Fab | D2: 5 | E2: 6000 | F2: 60 | G2: Shop | H2: =D2*E2 | I2: =D2*F2 | J2: =IFERROR(I2*INDEX(Inputs!$B$5:$B$8,MATCH(G2,Inputs!$A$5:$A$8,0)),0) | K2: =H2+J2 | L2: 10 | N2: Example row: MCE-built; qty x unit material + qty x hrs x shop rate
A3: A. Dry ingredients | B3: Load cells and weight controller per unloader | C3: Buyout | D3: 5 | E3: 4000 | F3: 0 | H3: =D3*E3 | I3: =D3*F3 | J3: =IFERROR(I3*INDEX(Inputs!$B$5:$B$8,MATCH(G3,Inputs!$A$5:$A$8,0)),0) | K3: =H3+J3 | L3: 4 | N3: Loss-in-weight on each tote
A4: A. Dry ingredients | B4: Hoist and trolley per unloader | C4: Buyout | D4: 5 | E4: 3000 | F4: 0 | H4: =D4*E4 | I4: =D4*F4 | J4: =IFERROR(I4*INDEX(Inputs!$B$5:$B$8,MATCH(G4,Inputs!$A$5:$A$8,0)),0) | K4: =H4+J4 | L4: 4
A5: A. Dry ingredients | B5: Micro skid feeders (premix + additive) | C5: Buyout | D5: 2 | E5: 12000 | F5: 0 | H5: =D5*E5 | I5: =D5*F5 | J5: =IFERROR(I5*INDEX(Inputs!$B$5:$B$8,MATCH(G5,Inputs!$A$5:$A$8,0)),0) | K5: =H5+J5 | L5: 10 | N5: Loss-in-weight micro feeders, CPM/Beta Raven or Sudenga class
A6: A. Dry ingredients | B6: Micro skid frame and refill hoppers | C6: Fab | D6: 1 | E6: 5000 | F6: 100 | G6: Shop | H6: =D6*E6 | I6: =D6*F6 | J6: =IFERROR(I6*INDEX(Inputs!$B$5:$B$8,MATCH(G6,Inputs!$A$5:$A$8,0)),0) | K6: =H6+J6 | L6: 8
A7: A. Dry ingredients | B7: Collecting screw conveyor to cook | C7: Fab | D7: 1 | E7: 5000 | F7: 80 | G7: Shop | H7: =D7*E7 | I7: =D7*F7 | J7: =IFERROR(I7*INDEX(Inputs!$B$5:$B$8,MATCH(G7,Inputs!$A$5:$A$8,0)),0) | K7: =H7+J7 | L7: 6
A8: A. Dry ingredients | B8: Dust pickup / bin vent | C8: Buyout | D8: 1 | E8: 8000 | F8: 0 | H8: =D8*E8 | I8: =D8*F8 | J8: =IFERROR(I8*INDEX(Inputs!$B$5:$B$8,MATCH(G8,Inputs!$A$5:$A$8,0)),0) | K8: =H8+J8 | L8: 6
A9: B. Molasses | B9: Heated, insulated molasses tank (10-12k gal) | C9: Buyout | D9: 1 | E9: 35000 | F9: 0 | H9: =D9*E9 | I9: =D9*F9 | J9: =IFERROR(I9*INDEX(Inputs!$B$5:$B$8,MATCH(G9,Inputs!$A$5:$A$8,0)),0) | K9: =H9+J9 | L9: 12
A10: B. Molasses | B10: Unload and transfer pumps | C10: Buyout | D10: 2 | E10: 7000 | F10: 0 | H10: =D10*E10 | I10: =D10*F10 | J10: =IFERROR(I10*INDEX(Inputs!$B$5:$B$8,MATCH(G10,Inputs!$A$5:$A$8,0)),0) | K10: =H10+J10 | L10: 6
A11: B. Molasses | B11: Molasses flow meter | C11: Buyout | D11: 1 | E11: 8000 | F11: 0 | H11: =D11*E11 | I11: =D11*F11 | J11: =IFERROR(I11*INDEX(Inputs!$B$5:$B$8,MATCH(G11,Inputs!$A$5:$A$8,0)),0) | K11: =H11+J11 | L11: 8
A12: B. Molasses | B12: Molasses piping, valves, heat tracing | C12: Fab | D12: 1 | E12: 10000 | F12: 120 | G12: Shop | H12: =D12*E12 | I12: =D12*F12 | J12: =IFERROR(I12*INDEX(Inputs!$B$5:$B$8,MATCH(G12,Inputs!$A$5:$A$8,0)),0) | K12: =H12+J12 | L12: 4
A13: C. 3-stage cook | B13: Jacketed auger / mixing conveyor stage (SS304) | C13: Fab | D13: 3 | E13: 18000 | F13: 220 | G13: Shop | H13: =D13*E13 | I13: =D13*F13 | J13: =IFERROR(I13*INDEX(Inputs!$B$5:$B$8,MATCH(G13,Inputs!$A$5:$A$8,0)),0) | K13: =H13+J13 | L13: 14 | N13: MCE design; 3 stages
A14: C. 3-stage cook | B14: Gearmotors and drives, cook stages | C14: Buyout | D14: 3 | E14: 4500 | F14: 0 | H14: =D14*E14 | I14: =D14*F14 | J14: =IFERROR(I14*INDEX(Inputs!$B$5:$B$8,MATCH(G14,Inputs!$A$5:$A$8,0)),0) | K14: =H14+J14 | L14: 8
A15: C. 3-stage cook | B15: Heat source: packaged hot-oil heater or steam boiler | C15: Buyout | D15: 1 | E15: 65000 | F15: 0 | H15: =D15*E15 | I15: =D15*F15 | J15: =IFERROR(I15*INDEX(Inputs!$B$5:$B$8,MATCH(G15,Inputs!$A$5:$A$8,0)),0) | K15: =H15+J15 | L15: 16 | N15: Usually the longest lead buyout
A16: C. 3-stage cook | B16: Heating piping and insulation | C16: Fab | D16: 1 | E16: 8000 | F16: 120 | G16: Shop | H16: =D16*E16 | I16: =D16*F16 | J16: =IFERROR(I16*INDEX(Inputs!$B$5:$B$8,MATCH(G16,Inputs!$A$5:$A$8,0)),0) | K16: =H16+J16 | L16: 6
A17: C. 3-stage cook | B17: Vapor vent hood and duct | C17: Fab | D17: 1 | E17: 4000 | F17: 60 | G17: Shop | H17: =D17*E17 | I17: =D17*F17 | J17: =IFERROR(I17*INDEX(Inputs!$B$5:$B$8,MATCH(G17,Inputs!$A$5:$A$8,0)),0) | K17: =H17+J17 | L17: 6
A18: C. 3-stage cook | B18: Platform, stairs and handrail | C18: Fab | D18: 1 | E18: 15000 | F18: 240 | G18: Shop | H18: =D18*E18 | I18: =D18*F18 | J18: =IFERROR(I18*INDEX(Inputs!$B$5:$B$8,MATCH(G18,Inputs!$A$5:$A$8,0)),0) | K18: =H18+J18 | L18: 8
A19: D. Pour turntable | B19: Rotary pour/cure turntable structure | C19: Fab | D19: 1 | E19: 14000 | F19: 260 | G19: Shop | H19: =D19*E19 | I19: =D19*F19 | J19: =IFERROR(I19*INDEX(Inputs!$B$5:$B$8,MATCH(G19,Inputs!$A$5:$A$8,0)),0) | K19: =H19+J19 | L19: 12
A20: D. Pour turntable | B20: Slew bearing and indexing drive | C20: Buyout | D20: 1 | E20: 15000 | F20: 0 | H20: =D20*E20 | I20: =D20*F20 | J20: =IFERROR(I20*INDEX(Inputs!$B$5:$B$8,MATCH(G20,Inputs!$A$5:$A$8,0)),0) | K20: =H20+J20 | L20: 12
A21: D. Pour turntable | B21: Pour valve and scale platform | C21: Buyout | D21: 1 | E21: 15000 | F21: 0 | H21: =D21*E21 | I21: =D21*F21 | J21: =IFERROR(I21*INDEX(Inputs!$B$5:$B$8,MATCH(G21,Inputs!$A$5:$A$8,0)),0) | K21: =H21+J21 | L21: 8
A22: E. Cure tunnel | B22: Tunnel conveyor, per 10 ft section | C22: Fab | D22: 10 | E22: 2500 | F22: 30 | G22: Shop | H22: =D22*E22 | I22: =D22*F22 | J22: =IFERROR(I22*INDEX(Inputs!$B$5:$B$8,MATCH(G22,Inputs!$A$5:$A$8,0)),0) | K22: =H22+J22 | L22: 10 | N22: Qty = tunnel length / 10 ft; length set by cure time in FEED
A23: E. Cure tunnel | B23: Tunnel enclosure panels, per 10 ft section | C23: Fab | D23: 10 | E23: 1200 | F23: 12 | G23: Shop | H23: =D23*E23 | I23: =D23*F23 | J23: =IFERROR(I23*INDEX(Inputs!$B$5:$B$8,MATCH(G23,Inputs!$A$5:$A$8,0)),0) | K23: =H23+J23 | L23: 8 | N23: Same qty as conveyor sections
A24: E. Cure tunnel | B24: Supply fans | C24: Buyout | D24: 2 | E24: 5000 | F24: 0 | H24: =D24*E24 | I24: =D24*F24 | J24: =IFERROR(I24*INDEX(Inputs!$B$5:$B$8,MATCH(G24,Inputs!$A$5:$A$8,0)),0) | K24: =H24+J24 | L24: 8
A25: E. Cure tunnel | B25: Off-gas exhaust fan and stack | C25: Buyout | D25: 1 | E25: 10000 | F25: 0 | H25: =D25*E25 | I25: =D25*F25 | J25: =IFERROR(I25*INDEX(Inputs!$B$5:$B$8,MATCH(G25,Inputs!$A$5:$A$8,0)),0) | K25: =H25+J25 | L25: 8
A26: F. Robot and wrap | B26: Robot palletizer with controller (reman FANUC-class) | C26: Buyout | D26: 1 | E26: 60000 | F26: 0 | H26: =D26*E26 | I26: =D26*F26 | J26: =IFERROR(I26*INDEX(Inputs!$B$5:$B$8,MATCH(G26,Inputs!$A$5:$A$8,0)),0) | K26: =H26+J26 | L26: 12 | M26: Robot | N26: New robot adds roughly $30-50k
A27: F. Robot and wrap | B27: End-of-arm tub gripper | C27: Fab | D27: 1 | E27: 6000 | F27: 80 | G27: Shop | H27: =D27*E27 | I27: =D27*F27 | J27: =IFERROR(I27*INDEX(Inputs!$B$5:$B$8,MATCH(G27,Inputs!$A$5:$A$8,0)),0) | K27: =H27+J27 | L27: 6 | M27: Robot
A28: F. Robot and wrap | B28: Robot fence, scanners, safety interlocks | C28: Buyout | D28: 1 | E28: 18000 | F28: 0 | H28: =D28*E28 | I28: =D28*F28 | J28: =IFERROR(I28*INDEX(Inputs!$B$5:$B$8,MATCH(G28,Inputs!$A$5:$A$8,0)),0) | K28: =H28+J28 | L28: 6 | M28: Robot
A29: F. Robot and wrap | B29: Semi-automatic stretch wrapper | C29: Buyout | D29: 1 | E29: 15000 | F29: 0 | H29: =D29*E29 | I29: =D29*F29 | J29: =IFERROR(I29*INDEX(Inputs!$B$5:$B$8,MATCH(G29,Inputs!$A$5:$A$8,0)),0) | K29: =H29+J29 | L29: 6
A30: G. Controls | B30: PLC, HMI, VFDs and panel hardware | C30: Buyout | D30: 1 | E30: 65000 | F30: 0 | H30: =D30*E30 | I30: =D30*F30 | J30: =IFERROR(I30*INDEX(Inputs!$B$5:$B$8,MATCH(G30,Inputs!$A$5:$A$8,0)),0) | K30: =H30+J30 | L30: 12
A31: G. Controls | B31: Control panel build | C31: Labor | D31: 1 | E31: 0 | F31: 250 | G31: Shop | H31: =D31*E31 | I31: =D31*F31 | J31: =IFERROR(I31*INDEX(Inputs!$B$5:$B$8,MATCH(G31,Inputs!$A$5:$A$8,0)),0) | K31: =H31+J31 | L31: 4
A32: G. Controls | B32: PLC/HMI programming and robot integration | C32: Labor | D32: 1 | E32: 0 | F32: 450 | G32: Controls | H32: =D32*E32 | I32: =D32*F32 | J32: =IFERROR(I32*INDEX(Inputs!$B$5:$B$8,MATCH(G32,Inputs!$A$5:$A$8,0)),0) | K32: =H32+J32
A33: H. Engineering | B33: Detailed design, drawings and project management | C33: Labor | D33: 1 | E33: 0 | F33: 550 | G33: Eng | H33: =D33*E33 | I33: =D33*F33 | J33: =IFERROR(I33*INDEX(Inputs!$B$5:$B$8,MATCH(G33,Inputs!$A$5:$A$8,0)),0) | K33: =H33+J33
A34: I. Start-up services | B34: Start-up services: 1 technician, about 5 days on site | C34: Labor | D34: 1 | E34: 0 | F34: 50 | G34: Controls | H34: =D34*E34 | I34: =D34*F34 | J34: =IFERROR(I34*INDEX(Inputs!$B$5:$B$8,MATCH(G34,Inputs!$A$5:$A$8,0)),0) | K34: =H34+J34 | N34: Sold at $13,800 fixed (proposal item 34); installation and freight by others
A35: I. Start-up services | B35: Start-up travel and expenses | C35: Buyout | D35: 1 | E35: 3500 | F35: 0 | H35: =D35*E35 | I35: =D35*F35 | J35: =IFERROR(I35*INDEX(Inputs!$B$5:$B$8,MATCH(G35,Inputs!$A$5:$A$8,0)),0) | K35: =H35+J35
A36: Total | H36: =SUM(H2:H35) | I36: =SUM(I2:I35) | J36: =SUM(J2:J35) | K36: =SUM(K2:K35)
A38: Legend: blue cells are inputs (qty, unit cost, hours, lead time). Labor class pulls the rate from Inputs. Row 2 is the worked example.
